django_cockroachdb/__init__.py
django_cockroachdb/base.py
django_cockroachdb/client.py
django_cockroachdb/creation.py
django_cockroachdb/features.py
django_cockroachdb/functions.py
django_cockroachdb/introspection.py
django_cockroachdb/lookups.py
django_cockroachdb/operations.py
django_cockroachdb/schema.py
django_cockroachdb/utils.py
django_cockroachdb-6.0.dist-info/licenses/LICENSE
django_cockroachdb_gis/__init__.py
django_cockroachdb_gis/base.py
django_cockroachdb_gis/features.py
django_cockroachdb_gis/functions.py
django_cockroachdb_gis/introspection.py
django_cockroachdb_gis/operations.py
django_cockroachdb_gis/schema.py
django_cockroachdb-6.0.dist-info/METADATA
django_cockroachdb-6.0.dist-info/WHEEL
django_cockroachdb-6.0.dist-info/top_level.txt
django_cockroachdb-6.0.dist-info/RECORD
