Metadata-Version: 2.4
Name: django-cockroachdb
Version: 6.0
Summary: Django backend for CockroachDB
Home-page: https://github.com/cockroachdb/django-cockroachdb
Maintainer: Cockroach Labs
Maintainer-email: python@cockroachlabs.com
License: Apache Software License
Project-URL: Source, https://github.com/cockroachdb/django-cockroachdb
Project-URL: Tracker, https://github.com/cockroachdb/django-cockroachdb/issues
Classifier: Development Status :: 5 - Production/Stable
Classifier: Framework :: Django
Classifier: Framework :: Django :: 6.0
Classifier: License :: OSI Approved :: Apache Software License
Classifier: Operating System :: OS Independent
Classifier: Programming Language :: Python
Classifier: Programming Language :: Python :: 3
Classifier: Programming Language :: Python :: 3.12
Classifier: Programming Language :: Python :: 3.13
Classifier: Programming Language :: Python :: 3.14
Requires-Python: >=3.12
License-File: LICENSE
Requires-Dist: django<6.1,>=6.0
Dynamic: license-file
